{
  "hash": "9ede540c",
  "configHash": "978ec6c5",
  "lockfileHash": "ad60e644",
  "browserHash": "b072f88c",
  "optimized": {
    "vue": {
      "src": "../../../node_modules/vue/dist/vue.runtime.esm-bundler.js",
      "file": "vue.js",
      "fileHash": "30955812",
      "needsInterop": false
    },
    "vitepress > @vue/devtools-api": {
      "src": "../../../node_modules/@vue/devtools-api/dist/index.js",
      "file": "vitepress___@vue_devtools-api.js",
      "fileHash": "3f532500",
      "needsInterop": false
    },
    "vitepress > @vueuse/core": {
      "src": "../../../node_modules/@vueuse/core/index.mjs",
      "file": "vitepress___@vueuse_core.js",
      "fileHash": "57105672",
      "needsInterop": false
    },
    "vitepress > @vueuse/integrations/useFocusTrap": {
      "src": "../../../node_modules/@vueuse/integrations/useFocusTrap.mjs",
      "file": "vitepress___@vueuse_integrations_useFocusTrap.js",
      "fileHash": "600de52d",
      "needsInterop": false
    },
    "vitepress > mark.js/src/vanilla.js": {
      "src": "../../../node_modules/mark.js/src/vanilla.js",
      "file": "vitepress___mark__js_src_vanilla__js.js",
      "fileHash": "393dfacc",
      "needsInterop": false
    },
    "vitepress > minisearch": {
      "src": "../../../node_modules/minisearch/dist/es/index.js",
      "file": "vitepress___minisearch.js",
      "fileHash": "5c9d4026",
      "needsInterop": false
    },
    "vue-use-spring": {
      "src": "../../../node_modules/vue-use-spring/dist/index.mjs",
      "file": "vue-use-spring.js",
      "fileHash": "4e7ac9a1",
      "needsInterop": false
    }
  },
  "chunks": {
    "chunk-ENS6V5QA": {
      "file": "chunk-ENS6V5QA.js"
    },
    "chunk-Z5MM7V3J": {
      "file": "chunk-Z5MM7V3J.js"
    },
    "chunk-VJWGEPT5": {
      "file": "chunk-VJWGEPT5.js"
    }
  }
}